calla/__init__.py
calla/__main__.py
calla/__version__.py
calla/article.py
calla/config.py
calla/forms.py
calla/model.py
calla/process.py
calla/utils.py
calla/views.py
calla/config/defaultconf.py
calla/static/css/app.ebead974cbbbfd5faa5c9e58d81aab1d.css
calla/static/css/app.ebead974cbbbfd5faa5c9e58d81aab1d.css.map
calla/static/fonts/ionicons.05acfdb.woff
calla/static/fonts/ionicons.24712f6.ttf
calla/static/fonts/ionicons.2c2ae06.eot
calla/static/img/ionicons.621bd38.svg
calla/static/js/app.4bd46ff1052e2880f943.js
calla/static/js/app.4bd46ff1052e2880f943.js.map
calla/static/js/manifest.4dbab555adced95e4c3b.js
calla/static/js/manifest.4dbab555adced95e4c3b.js.map
calla/static/js/vendor.f83a88205277b01dc10c.js
calla/static/js/vendor.f83a88205277b01dc10c.js.map
calla/templates/index.html
calla/templates/layout.html
calla/templates/settings.html
calla/templates/admin/server_setting.html
calla/templates/article/edit.html
calla/templates/article/index.html
calla/templates/dist/index.html
calla-0.0.1.dist-info/DESCRIPTION.rst
calla-0.0.1.dist-info/METADATA
calla-0.0.1.dist-info/RECORD
calla-0.0.1.dist-info/WHEEL
calla-0.0.1.dist-info/entry_points.txt
calla-0.0.1.dist-info/metadata.json
calla-0.0.1.dist-info/top_level.txt
