Metadata-Version: 2.0
Name: calla
Version: 0.0.1
Summary: a static blog.
Home-page: https://github.com/xiaojieluo/calla
Author: Xiaojie Luo
Author-email: xiaojieluoff@gmail.com
License: Apache 2.0
Platform: UNKNOWN
Classifier: Development Status :: 5 - Production/Stable
Classifier: Intended Audience :: Developers
Classifier: Natural Language :: English
Classifier: License :: OSI Approved :: Apache Software License
Classifier: Programming Language :: Python
Classifier: Programming Language :: Python :: 3
Classifier: Programming Language :: Python :: 3.3
Classifier: Programming Language :: Python :: 3.4
Classifier: Programming Language :: Python :: 3.5
Classifier: Programming Language :: Python :: 3.6
Classifier: Programming Language :: Python :: Implementation :: CPython
Classifier: Programming Language :: Python :: Implementation :: PyPy
Requires-Dist: flask (>=0.12.2)
Requires-Dist: flask-WTF (>=0.14.2)
Provides-Extra: security
Requires-Dist: pyOpenSSL (>=0.14); extra == 'security'
Requires-Dist: cryptography (>=1.3.4); extra == 'security'
Requires-Dist: idna (>=2.0.0); extra == 'security'
Provides-Extra: socks
Requires-Dist: PySocks (!=1.5.7,>=1.5.6); extra == 'socks'
Provides-Extra: socks
Requires-Dist: win-inet-pton; sys_platform == "win32" and (python_version == "2.7" or python_version == "2.6") and extra == 'socks'
